{
  "fields": [
    {
      "type": "checkbox",
      "label": "Enable Name",
      "value": true,
      "validationRules": [],
      "businessRules": [
        {
          "targetField": "Name",
          "action": "enable",
          "condition": "isChecked"
        }
      ]
    },
    {
      "type": "text",
      "label": "Name",
      "value": "",
      "enabled": true,
      "validationRules": ["required"]
    },
    {
      "type": "number",
      "label": "Age",
      "value": "18",
      "validationRules": ["required"]
    },
    {
      "type": "dropdown",
      "label": "Gender",
      "value": "Male",
      "options": ["Male", "Female", "Other"],
      "validationRules": ["required"]
    }
  ]
}
